daeman/__init__.py
daeman/daemon_manager.py
daeman-0.0.1.dist-info/DESCRIPTION.rst
daeman-0.0.1.dist-info/METADATA
daeman-0.0.1.dist-info/RECORD
daeman-0.0.1.dist-info/WHEEL
daeman-0.0.1.dist-info/metadata.json
daeman-0.0.1.dist-info/top_level.txt
