Metadata-Version: 2.0
Name: daeman
Version: 0.0.1
Summary: A daemon manager for python-daemon
Home-page: https://github.com/kktk-KO/daeman
Author: kktk
Author-email: kktkko3579@gmail.com
License: CC0
Keywords: daemon unix
Platform: UNKNOWN
Classifier: Development Status :: 3 - Alpha
Classifier: Intended Audience :: Developers
Classifier: License :: CC0 1.0 Universal (CC0 1.0) Public Domain Dedication
Classifier: Operating System :: POSIX
Classifier: Programming Language :: Python :: 2
Classifier: Programming Language :: Python :: 3
Requires-Dist: python-daemon
